dagster_async_executor/__init__.py
dagster_async_executor/executor.py
dagster_async_executor/executor_definition.py
dagster_async_executor/execution/__init__.py
dagster_async_executor/execution/plan/__init__.py
dagster_async_executor/execution/plan/compute.py
dagster_async_executor/execution/plan/compute_generator.py
dagster_async_executor/execution/plan/execute_plan.py
dagster_async_executor/execution/plan/execute_step.py
dagster_async_executor-0.0.2.dist-info/METADATA
dagster_async_executor-0.0.2.dist-info/WHEEL
dagster_async_executor-0.0.2.dist-info/top_level.txt
dagster_async_executor-0.0.2.dist-info/RECORD
