Metadata-Version: 2.4
Name: dagster-async-executor
Version: 0.0.2
Summary: Async Support for Dagster
Requires-Python: >=3.10
Requires-Dist: anyio>=4.12.0
Requires-Dist: dagster>=1.12.2
